pdfsh/__init__.py
pdfsh/__main__.py
pdfsh/body.py
pdfsh/cmdline.py
pdfsh/document.py
pdfsh/exceptions.py
pdfsh/header.py
pdfsh/objects.py
pdfsh/page.py
pdfsh/parser.py
pdfsh/pdfsh.py
pdfsh/shell.py
pdfsh/tokenizer.py
pdfsh/tokens.py
pdfsh/trailer.py
pdfsh/xrt.py
pdfsh/pdfminer/ccitt.py
pdfsh/pdfminer/lzw.py
pdfsh/pdfminer/utils.py
pdfsh-2024.4.dist-info/LICENSE
pdfsh-2024.4.dist-info/LICENSE.pdfminer.six
pdfsh-2024.4.dist-info/METADATA
pdfsh-2024.4.dist-info/WHEEL
pdfsh-2024.4.dist-info/entry_points.txt
pdfsh-2024.4.dist-info/top_level.txt
pdfsh-2024.4.dist-info/RECORD
