Metadata-Version: 2.1
Name: pdfsh
Version: 2024.4
Summary: minimal shell to investigate PDF files
Author-email: Mete Balci <metebalci@gmail.com>
Project-URL: Homepage, https://github.com/metebalci/pdfsh
Project-URL: Documentation, https://github.com/metebalci/pdfsh
Project-URL: Repository, https://github.com/metebalci/pdfsh.git
Project-URL: Issues, https://github.com/metebalci/pdfsh/issues
Project-URL: Changelog, https://github.com/metebalci/pdfsh/blob/master/README.md
Keywords: pdf
Classifier: Development Status :: 3 - Alpha
Classifier: Environment :: Console
Classifier: License :: OSI Approved :: GNU General Public License v3 or later (GPLv3+)
Classifier: Programming Language :: Python :: 3.8
Classifier: Topic :: Utilities
Requires-Python: >=3.8
License-File: LICENSE
License-File: LICENSE.pdfminer.six
Provides-Extra: dev
Requires-Dist: setuptools >=61.0 ; extra == 'dev'
Requires-Dist: black ; extra == 'dev'
Requires-Dist: pylint ; extra == 'dev'
Requires-Dist: build ; extra == 'dev'
Requires-Dist: twine ; extra == 'dev'
Requires-Dist: reuse ; extra == 'dev'
